iflow_mcp_obsidian_mcp_tool-1.0.0.dist-info/licenses/LICENSE
obsidian_mcp_server/config.py
obsidian_mcp_server/main.py
obsidian_mcp_server/mcp_server.py
obsidian_mcp_server/utils/__init__.py
obsidian_mcp_server/utils/daily_notes.py
obsidian_mcp_server/utils/exceptions.py
obsidian_mcp_server/utils/vault_reader.py
obsidian_mcp_server/utils/vault_search.py
obsidian_mcp_server/utils/vault_writer.py
iflow_mcp_obsidian_mcp_tool-1.0.0.dist-info/METADATA
iflow_mcp_obsidian_mcp_tool-1.0.0.dist-info/WHEEL
iflow_mcp_obsidian_mcp_tool-1.0.0.dist-info/entry_points.txt
iflow_mcp_obsidian_mcp_tool-1.0.0.dist-info/top_level.txt
iflow_mcp_obsidian_mcp_tool-1.0.0.dist-info/RECORD
