Metadata-Version: 2.4
Name: iflow-mcp_obsidian_mcp_tool
Version: 1.0.0
Summary: An MCP server exposing tools to interact with an Obsidian vault.
Author: Rwb3n / Gemini 2.5 pro
Project-URL: Homepage, https://github.com/Rwb3n/obsidian-mcp
Project-URL: Bug Tracker, https://github.com/Rwb3n/obsidian-mcp/issues
Classifier: Programming Language :: Python :: 3
Classifier: License :: OSI Approved :: MIT License
Classifier: Operating System :: OS Independent
Classifier: Topic :: Office/Business
Classifier: Topic :: Scientific/Engineering :: Interface Engine/Protocol Translator
Requires-Python: >=3.9
License-File: LICENSE
Requires-Dist: mcp
Requires-Dist: pydantic-settings
Requires-Dist: python-dotenv
Requires-Dist: pyyaml
Requires-Dist: fastapi
Requires-Dist: uvicorn[standard]
Requires-Dist: aiofiles
Requires-Dist: h11>=0.16.0
Dynamic: license-file
